{
  "pcbHeight": 120,
  "pcbWidth": 120,
  "availableGpio": [
    "4",
    "17",
    "27",
    "22",
    "5",
    "6",
    "13",
    "26",
    "18",
    "23",
    "24",
    "25",
    "12"
  ],
  "availableI2c": [
    "/dev/i2c-1"
  ],
  "availableSpi": [
    "/dev/spidev0.0"
  ],
  "availableSerial": [
    "/dev/spidev0.0"
  ],
  "part0": {
    "componentName": "physical-button-red",
    "componentWidth": "10mm",
    "componentHeight": "10mm",
    "componentX": 5,
    "componentY": 5,
    "gpio": [
      "4"
    ],
    "i2c": [],
    "spi": [],
    "serial": []
  }
}